censosine21/__init__.py
censosine21/censosine21.py
censosine21/entities/__init__.py
censosine21/entities/entities.py
censosine21-0.1.0.dist-info/LICENSE.md
censosine21-0.1.0.dist-info/METADATA
censosine21-0.1.0.dist-info/WHEEL
censosine21-0.1.0.dist-info/top_level.txt
censosine21-0.1.0.dist-info/RECORD
