Metadata-Version: 2.1
Name: censosine21
Version: 0.1.0
Summary: Python library to interact with the API of the National Institute of Statistics (INE ) of Spain that offers the data Dissemination System of the Population and Housing Censuses 2021 (SDC21). 
Home-page: https://github.com/sigdeletras/censosine21
Author: Patricio Soriano @sigdeletras
Author-email: pasoriano@gmail.com
License: MIT
Classifier: Development Status :: 3 - Alpha
Classifier: Intended Audience :: Developers
Classifier: Intended Audience :: Science/Research
Classifier: Operating System :: OS Independent
Classifier: Topic :: Software Development :: Build Tools
Classifier: License :: OSI Approved :: MIT License
Classifier: Programming Language :: Python :: 3
License-File: LICENSE.md
Requires-Dist: requests
